<?xml version="1.0" encoding="utf-8" ?>
<dwsync>
<file name="config.php" server="elephant-red-9cf3243993ed3f6f.znlc.jp//pc4353.net/" local="132197388753060578" remote="132197389800000000" Dst="0" />
<file name="instructor.php" server="elephant-red-9cf3243993ed3f6f.znlc.jp//pc4353.net/" local="132276902968110905" remote="132276903000000000" Dst="0" />
<file name="about.php" server="elephant-red-9cf3243993ed3f6f.znlc.jp//pc4353.net/" local="131539074278844186" remote="131539077600000000" Dst="0" />
<file name="voice.php" server="elephant-red-9cf3243993ed3f6f.znlc.jp//pc4353.net/" local="131580608196641576" remote="131580616800000000" Dst="0" />
<file name="certify.php" server="elephant-red-9cf3243993ed3f6f.znlc.jp//pc4353.net/" local="132128252111341609" remote="132128259000000000" Dst="0" />
<file name="mos.php" server="elephant-red-9cf3243993ed3f6f.znlc.jp//pc4353.net/" local="131576268875894734" remote="131576271600000000" Dst="0" />
<file name="certify_contact_complete.php" server="elephant-red-9cf3243993ed3f6f.znlc.jp//pc4353.net/" local="131690269251311886" remote="131690276400000000" Dst="0" />
<file name="certify_contact_confirm.php" server="elephant-red-9cf3243993ed3f6f.znlc.jp//pc4353.net/" local="131690269254642077" remote="131690276400000000" Dst="0" />
<file name="sokudoku.php" server="elephant-red-9cf3243993ed3f6f.znlc.jp//pc4353.net/" local="132103952153392027" remote="132103951800000000" Dst="0" />
<file name="sokudoku_contact_complete.php" server="elephant-red-9cf3243993ed3f6f.znlc.jp//pc4353.net/" local="132103952154823254" remote="132103951800000000" Dst="0" />
<file name="sokudoku_contact_confirm.php" server="elephant-red-9cf3243993ed3f6f.znlc.jp//pc4353.net/" local="132103952156202587" remote="132103951800000000" Dst="0" />
<file name="tablet.php" server="elephant-red-9cf3243993ed3f6f.znlc.jp//pc4353.net/" local="132145614166520634" remote="132145639800000000" Dst="0" />
<file name="bb_basic.php" server="elephant-red-9cf3243993ed3f6f.znlc.jp//pc4353.net/" local="132145614102154435" remote="132145639800000000" Dst="0" />
<file name="bb_excel.php" server="elephant-red-9cf3243993ed3f6f.znlc.jp//pc4353.net/" local="132145614105272944" remote="132145639800000000" Dst="0" />
<file name="bb_powerpoint.php" server="elephant-red-9cf3243993ed3f6f.znlc.jp//pc4353.net/" local="132145614108201544" remote="132145639800000000" Dst="0" />
<file name="bb_word.php" server="elephant-red-9cf3243993ed3f6f.znlc.jp//pc4353.net/" local="132145614113449620" remote="132145639800000000" Dst="0" />
<file name="brain_training.php" server="elephant-red-9cf3243993ed3f6f.znlc.jp//pc4353.net/" local="132145614116937949" remote="132145639800000000" Dst="0" />
<file name="d_photo_master.php" server="elephant-red-9cf3243993ed3f6f.znlc.jp//pc4353.net/" local="132145614120206386" remote="132145639800000000" Dst="0" />
<file name="digital_basic.php" server="elephant-red-9cf3243993ed3f6f.znlc.jp//pc4353.net/" local="132145614123604783" remote="132145639800000000" Dst="0" />
<file name="excel.php" server="elephant-red-9cf3243993ed3f6f.znlc.jp//pc4353.net/" local="132145614127272999" remote="132145639800000000" Dst="0" />
<file name="internet_master.php" server="elephant-red-9cf3243993ed3f6f.znlc.jp//pc4353.net/" local="132145614130511527" remote="132145639800000000" Dst="0" />
<file name="line.php" server="elephant-red-9cf3243993ed3f6f.znlc.jp//pc4353.net/" local="132145614134159806" remote="132145639800000000" Dst="0" />
<file name="nenga.php" server="elephant-red-9cf3243993ed3f6f.znlc.jp//pc4353.net/" local="132145614137438136" remote="132145639800000000" Dst="0" />
<file name="outlook_mail.php" server="elephant-red-9cf3243993ed3f6f.znlc.jp//pc4353.net/" local="132145614140917093" remote="132145639800000000" Dst="0" />
<file name="pc_basic.php" server="elephant-red-9cf3243993ed3f6f.znlc.jp//pc4353.net/" local="132145614144775249" remote="132145639800000000" Dst="0" />
<file name="powerpoint.php" server="elephant-red-9cf3243993ed3f6f.znlc.jp//pc4353.net/" local="132145614148583823" remote="132145639800000000" Dst="0" />
<file name="smartphone.php" server="elephant-red-9cf3243993ed3f6f.znlc.jp//pc4353.net/" local="132145614151992229" remote="132145639800000000" Dst="0" />
<file name="typing.php" server="elephant-red-9cf3243993ed3f6f.znlc.jp//pc4353.net/" local="132145614168789546" remote="132145639800000000" Dst="0" />
<file name="word.php" server="elephant-red-9cf3243993ed3f6f.znlc.jp//pc4353.net/" local="132145614174566788" remote="132145640400000000" Dst="0" />
<file name="word_craft.php" server="elephant-red-9cf3243993ed3f6f.znlc.jp//pc4353.net/" local="132145614178734791" remote="132145640400000000" Dst="0" />
<file name="gakuwari.php" server="elephant-red-9cf3243993ed3f6f.znlc.jp//pc4353.net/" local="132180108555704483" remote="132180151800000000" Dst="0" />
<file name="rehire.php" server="elephant-red-9cf3243993ed3f6f.znlc.jp//pc4353.net/" local="132253536107935410" remote="132253554600000000" Dst="0" />
<file name="start_check.php" server="elephant-red-9cf3243993ed3f6f.znlc.jp//pc4353.net/" local="132253536110854022" remote="132253554600000000" Dst="0" />
</dwsync>